Metadata-Version: 2.1
Name: geometry-box
Version: 0.1.2
Summary: A simple package for working with basic geometry shapes
Author: Rajesh Nakka
Author-email: 33rajesh@gmail.com
Classifier: Programming Language :: Python :: 3
Classifier: License :: OSI Approved :: MIT License
Classifier: Operating System :: OS Independent
Requires-Python: >=3.9
License-File: LICENSE
